{
  "projects": [
    {
      "img": "https://i.imgur.com/qse9tXO.jpg",
      "title": "Recipe Finder Web App",
      "description": "Simple web app to help users find recipes with what they have on hand.",
      "link": "https://github.com/Fareen-Khan/recipe-finder-app"
    },
    {
      "img": "https://i.imgur.com/08lHJ1L.png",
      "title": "Phantom Wallet Webpage",
      "description": "Simple webpage that showcases a pseudo application.",
      "link": ""
    },
    {
      "img": "https://i.imgur.com/VFakYxa.png",
      "title": "Stocks Discord Bot",
      "description": "A Discord bot that allows user to keep track of stock prices in real time.",
      "link": "https://github.com/Fareen-Khan/StocksBot"
    },
    {
      "img": "https://i.imgur.com/awMiFxK.png",
      "title": "Web Scrapping Discord Bot",
      "description": "Unique bot that returns COVID-19 statistics",
      "link": "https://github.com/Fareen-Khan/Discord-Bot"
    }
  ]
}
